[
  {
    "email": "waldo.bergnaum@yahoo.com",
    "name": "Jamar Flatley",
    "id": "3bec7d3d-ddc3-4167-bef2-53a5aac44915"
  },
  {
    "email": "bernie.leannon@gmail.com",
    "name": "Liz Cassin",
    "id": "b10c1016-2eee-480b-9409-bc2ddb980d42"
  },
  {
    "email": "ryann.johnston@gmail.com",
    "name": "Ezekiel Konopelski",
    "id": "01b55082-4076-4be7-9259-ed032185e24c"
  },
  {
    "email": "evan.daugherty@hotmail.com",
    "name": "Mr. Quinn Nienow",
    "id": "9834d358-6b05-4811-9377-8aa261dd7cbf"
  }
]